liquidcli/__init__.py
liquidcli/__version__.py
liquidcli/client.py
liquidcli/data.py
liquidcli/decoder.py
liquidcli-0.0.25.dist-info/LICENSE
liquidcli-0.0.25.dist-info/METADATA
liquidcli-0.0.25.dist-info/WHEEL
liquidcli-0.0.25.dist-info/top_level.txt
liquidcli-0.0.25.dist-info/RECORD
