Metadata-Version: 2.1
Name: liquidcli
Version: 0.0.25
Summary: A small example package
Home-page: https://github.com/suzuito/liquid-python
Author: Suzuito
Author-email: suzuito3@gmail.com
License: UNKNOWN
Platform: UNKNOWN
Classifier: Programming Language :: Python :: 3.7
Classifier: License :: OSI Approved :: MIT License
Classifier: Operating System :: OS Independent
Requires-Python: >=3.7
